fcwt/__init__.py
fcwt/_fcwt.cpython-310-darwin.so
fcwt/boilerplate.py
fcwt/fcwt.cpp
fcwt/fcwt.h
fcwt/fcwt.py
fcwt/fcwt_wrap.cxx
fcwt/fftw3.h
fcwt/fftw3f.dll
fcwt/fftw3f.lib
fcwt/libfftw3f_ompl.so
fcwt/libfftw3f_ompmac.a
fcwt/libfftw3fl.so
fcwt/libfftw3fmac.a
fcwt/libomp.a
fcwt/omp.h
fCWT-0.1.18.dist-info/LICENSE.txt
fCWT-0.1.18.dist-info/METADATA
fCWT-0.1.18.dist-info/WHEEL
fCWT-0.1.18.dist-info/top_level.txt
fCWT-0.1.18.dist-info/RECORD
