Metadata-Version: 2.1
Name: fCWT
Version: 0.1.18
Summary: A Python wrapper around the highly optimized C++ library for very fast calculation of the Continuous Wavelet Transform.
Author: Lukas P.A. Arts
Author-email: l.p.a.arts@uu.nl
Project-URL: url, https://github.com/fastlib/fCWT
Classifier: Programming Language :: Python :: 3
Classifier: Intended Audience :: Science/Research
Classifier: Intended Audience :: Developers
Classifier: Topic :: Software Development :: Libraries
Classifier: Topic :: Scientific/Engineering
Classifier: License :: OSI Approved :: Apache Software License
Classifier: Operating System :: OS Independent
Requires-Python: >=3.7
License-File: LICENSE.txt
Requires-Dist: numpy (>=1.14.5)
Provides-Extra: tests
Requires-Dist: pytest (<6) ; extra == 'tests'
